ssm_cli/__init__.py
ssm_cli/__main__.py
ssm_cli/aws.py
ssm_cli/cli.py
ssm_cli/cli_args.py
ssm_cli/config.py
ssm_cli/console.py
ssm_cli/instances.py
ssm_cli/logging.py
ssm_cli/xdg.py
ssm_cli/commands/__init__.py
ssm_cli/commands/base.py
ssm_cli/commands/list.py
ssm_cli/commands/setup.py
ssm_cli/commands/shell.py
ssm_cli/commands/ssh_proxy/__init__.py
ssm_cli/commands/ssh_proxy/channels.py
ssm_cli/commands/ssh_proxy/forwarding.py
ssm_cli/commands/ssh_proxy/server.py
ssm_cli/commands/ssh_proxy/shell.py
ssm_cli/commands/ssh_proxy/socket.py
ssm_cli/selectors/__init__.py
ssm_cli/selectors/first.py
ssm_cli/selectors/tui/__init__.py
ssm_cli/selectors/tui/posix.py
ssm_cli/selectors/tui/win.py
ssm_cli-1.0.2.dist-info/licenses/LICENCE
ssm_cli-1.0.2.dist-info/METADATA
ssm_cli-1.0.2.dist-info/WHEEL
ssm_cli-1.0.2.dist-info/entry_points.txt
ssm_cli-1.0.2.dist-info/top_level.txt
ssm_cli-1.0.2.dist-info/RECORD
