Metadata-Version: 2.4
Name: ssm-cli
Version: 1.0.2
Summary: CLI tool to help with SSM functionality, aimed at adminstrators
Author-email: Simon Fletcher <simon.fletcher@lexisnexisrisk.com>
License: MIT License
Project-URL: Homepage, https://github.com/simonfletcher-ln/ssm-cli
Project-URL: Issues, https://github.com/simonfletcher-ln/ssm-cli/issues
Classifier: Programming Language :: Python :: 3
Classifier: Operating System :: OS Independent
Classifier: License :: OSI Approved :: MIT License
Requires-Python: >=3.8
License-File: LICENCE
Requires-Dist: boto3
Requires-Dist: paramiko
Requires-Dist: rich-argparse
Requires-Dist: rich
Requires-Dist: confclasses>=0.3.2
Requires-Dist: xdg_base_dirs
Dynamic: license-file
